cmo_databaseutils/__init__.py
cmo_databaseutils/databaseutils.py
cmo_databaseutils-0.0.2.dist-info/METADATA
cmo_databaseutils-0.0.2.dist-info/WHEEL
cmo_databaseutils-0.0.2.dist-info/top_level.txt
cmo_databaseutils-0.0.2.dist-info/RECORD
