Metadata-Version: 2.1
Name: cmo-databaseutils
Version: 0.0.2
Summary: Connect to databases from Python
Home-page: https://Cmotions@dev.azure.com/Cmotions/Packages/_git/cmo_databaseutils
Author: Jeanine Schoonemann
Author-email: service@cmotions.nl
Requires-Python: >=3.6
Requires-Dist: sqlalchemy (>=1.4.7)
Requires-Dist: bcpy (>=0.1.8)
Requires-Dist: pandas (>=1.1.5)
Requires-Dist: pyodbc (>=4.0.30)
Requires-Dist: urllib3 (>=1.26.4)
Requires-Dist: cryptography (>=35.0.0)
Provides-Extra: dev
Requires-Dist: black ; extra == 'dev'
Requires-Dist: jupyterlab ; extra == 'dev'
Requires-Dist: pytest (>=6.2.4) ; extra == 'dev'
Requires-Dist: python-dotenv ; extra == 'dev'
Requires-Dist: ipykernel ; extra == 'dev'
Requires-Dist: pydataset ; extra == 'dev'
Requires-Dist: twine ; extra == 'dev'
